jsdc_loader/__init__.py
jsdc_loader/dumper.py
jsdc_loader/file_ops.py
jsdc_loader/loader.py
jsdc_loader/tests.py
jsdc_loader/core/__init__.py
jsdc_loader/core/converter.py
jsdc_loader/core/type_handlers.py
jsdc_loader/core/types.py
jsdc_loader/core/validator.py
jsdc_loader-0.2.2.dist-info/METADATA
jsdc_loader-0.2.2.dist-info/WHEEL
jsdc_loader-0.2.2.dist-info/top_level.txt
jsdc_loader-0.2.2.dist-info/RECORD
