Metadata-Version: 2.4
Name: jsdc_loader
Version: 0.2.2
Summary: JSON Data Class Loader
Author-email: StanleyUKN <stanley09537000@gmail.com>
Classifier: Programming Language :: Python :: 3
Classifier: License :: OSI Approved :: MIT License
Classifier: Operating System :: OS Independent
Requires-Python: >=3.8
